apptweak/__init__.py
apptweak/android.py
apptweak/ios.py
apptweak/plateform.py
apptweak/ressource.py
apptweak-2.0.0.dist-info/LICENSE.txt
apptweak-2.0.0.dist-info/METADATA
apptweak-2.0.0.dist-info/WHEEL
apptweak-2.0.0.dist-info/top_level.txt
apptweak-2.0.0.dist-info/RECORD
