Metadata-Version: 2.1
Name: apptweak
Version: 2.0.0
Summary: access the apptweak-io API in an easier way
Home-page: https://github.com/apptweak/apptweak-api-python-library
Author: apptweak
Author-email: romain@apptweak.com
License: MIT
Classifier: Programming Language :: Python :: 3.7
License-File: LICENSE.txt
